README.md
setup.py
bin/gcptree
gcptree/__init__.py
gcptree/cache.py
gcptree/cli.py
gcptree/test_cache.py
gcptree/test_tree.py
gcptree/tree.py
gcptree.egg-info/PKG-INFO
gcptree.egg-info/SOURCES.txt
gcptree.egg-info/dependency_links.txt
gcptree.egg-info/not-zip-safe
gcptree.egg-info/requires.txt
gcptree.egg-info/top_level.txt