Metadata-Version: 2.1
Name: gcptree
Version: 0.1.5
Summary: List your GCP Org heirachy as a tree in JSON or Text
Home-page: http://github.com/onetwopunch/gcptree
Author: Ryan Canty
Author-email: onetwopunch@pm.me
License: MIT
Platform: UNKNOWN
